dotenv_stripout/__init__.py
dotenv_stripout/__main__.py
dotenv_stripout/cli.py
dotenv_stripout/git.py
dotenv_stripout/install.py
dotenv_stripout/stripout.py
dotenv_stripout-0.1.3.dist-info/entry_points.txt
dotenv_stripout-0.1.3.dist-info/LICENSE.md
dotenv_stripout-0.1.3.dist-info/WHEEL
dotenv_stripout-0.1.3.dist-info/METADATA
dotenv_stripout-0.1.3.dist-info/RECORD
