Metadata-Version: 2.1
Name: dotenv-stripout
Version: 0.1.3
Summary: Strip secrets from .env files
Home-page: https://github.com/harrisonpim/dotenv-stripout
Author: Harrison Pim
Author-email: hello@harrisonpim.com
Requires-Python: >=3.6
Classifier: License :: OSI Approved :: MIT License
Requires-Dist: typer>=0.3.2
Requires-Dist: black>=19.10b0 ; extra == "dev"
Requires-Dist: flake8>=3.8.1 ; extra == "dev"
Requires-Dist: isort>=4.3.21 ; extra == "dev"
Requires-Dist: pytest>=6.2.4 ; extra == "dev"
Provides-Extra: dev
